faster_whisper/__init__.py
faster_whisper/audio.py
faster_whisper/feature_extractor.py
faster_whisper/tokenizer.py
faster_whisper/transcribe.py
faster_whisper/utils.py
faster_whisper/vad.py
faster_whisper/version.py
faster_whisper/assets/__init__.py
faster_whisper/assets/silero_decoder_v5.onnx
faster_whisper/assets/silero_encoder_v5.onnx
faster_whisper-1.2.0.dist-info/LICENSE
faster_whisper-1.2.0.dist-info/METADATA
faster_whisper-1.2.0.dist-info/WHEEL
faster_whisper-1.2.0.dist-info/top_level.txt
faster_whisper-1.2.0.dist-info/RECORD
