Metadata-Version: 2.1
Name: faster-whisper
Version: 1.2.0
Summary: Faster Whisper transcription with CTranslate2
Home-page: https://github.com/SYSTRAN/faster-whisper
Author: Guillaume Klein
License: MIT
Keywords: openai whisper speech ctranslate2 inference quantization transformer
Platform: UNKNOWN
Classifier: Development Status :: 4 - Beta
Classifier: Intended Audience :: Developers
Classifier: Intended Audience :: Science/Research
Classifier: License :: OSI Approved :: MIT License
Classifier: Programming Language :: Python :: 3
Classifier: Programming Language :: Python :: 3 :: Only
Classifier: Programming Language :: Python :: 3.9
Classifier: Programming Language :: Python :: 3.10
Classifier: Programming Language :: Python :: 3.11
Classifier: Topic :: Scientific/Engineering :: Artificial Intelligence
Requires-Python: >=3.9
Provides-Extra: conversion
Provides-Extra: dev
License-File: LICENSE
